ip_sync/__init__.py
ip_sync/main.py
ip_sync/providers.py
ip_sync/version.py
ip_sync/test/__init__.py
ip_sync/test/test_main.py
ip_sync/test/test_providers.py
ipsync-0.1.0.dist-info/entry_points.txt
ipsync-0.1.0.dist-info/top_level.txt
ipsync-0.1.0.dist-info/METADATA
ipsync-0.1.0.dist-info/DESCRIPTION.rst
ipsync-0.1.0.dist-info/metadata.json
ipsync-0.1.0.dist-info/WHEEL
ipsync-0.1.0.dist-info/RECORD
