Metadata-Version: 2.0
Name: ipsync
Version: 0.1.0
Summary: ipsync is a script to update multiple cloud DNS providers with your external IP address
Home-page: https://github.com/jon-walton/ipsync
Author: Jon Walton
Author-email: jonwalton@gmail.com
License: MIT
Platform: UNKNOWN
Classifier: Development Status :: 1 - Planning
Classifier: Natural Language :: English
Classifier: Operating System :: OS Independent
Classifier: Programming Language :: Python :: 3.3
Requires-Dist: PyYAML (>=3.11)
Requires-Dist: requests (>=2.5.1)
Requires-Dist: ipaddress (>=1.0.7)
Requires-Dist: mock
Requires-Dist: six (>=1.8.0)
Requires-Dist: docopt
Requires-Dist: schema (>=0.3.1)
Requires-Dist: apache-libcloud (>=0.16.0)
Requires-Dist: beautifulsoup4 (>=4.3.2)
